wagtail_related-0.1.0.dist-info/METADATA
wagtail_related-0.1.0.dist-info/RECORD
wagtail_related-0.1.0.dist-info/WHEEL
wagtail_related-0.1.0.dist-info/top_level.txt
wagtailrelated/__init__.py
wagtailrelated/apps.py
wagtailrelated/edit_handlers.py
wagtailrelated/source_fields.py
wagtailrelated/utils.py
wagtailrelated/wagtail_hooks.py
wagtailrelated/widgets.py
wagtailrelated/api/__init__.py
wagtailrelated/api/exceptions.py
wagtailrelated/api/serializers.py
wagtailrelated/api/urls.py
wagtailrelated/api/views.py
wagtailrelated/backends/__init__.py
wagtailrelated/backends/base.py
wagtailrelated/backends/dandelion.py
wagtailrelated/backends/elasticsearch5.py
wagtailrelated/backends/google_cloud_language.py
wagtailrelated/management/__init__.py
wagtailrelated/management/commands/__init__.py
wagtailrelated/management/commands/debug_autotagging.py
wagtailrelated/static/wagtailrelated/css/admin_widget.css
wagtailrelated/static/wagtailrelated/js/admin_widget.js
wagtailrelated/templates/wagtailrelated/edit_handlers/field.html
wagtailrelated/templates/wagtailrelated/edit_handlers/field_panel_field.html
wagtailrelated/templates/wagtailrelated/edit_handlers/single_field_panel.html
