Metadata-Version: 2.1
Name: wagtail-related
Version: 0.1.0
Summary: A module for Wagtail that finds related pages and tags for your pages.
Home-page: https://github.com/torchbox/wagtail-related
Author: Mikalai Radchuk
Author-email: mikalai.radchuk@torchbox.com
License: BSD
Platform: UNKNOWN
Classifier: Development Status :: 4 - Beta
Classifier: Environment :: Web Environment
Classifier: Intended Audience :: Developers
Classifier: License :: OSI Approved :: BSD License
Classifier: Operating System :: OS Independent
Classifier: Programming Language :: Python
Classifier: Programming Language :: Python :: 3.6
Classifier: Framework :: Django
Classifier: Framework :: Django :: 2.0
Classifier: Framework :: Wagtail
Classifier: Framework :: Wagtail :: 2
Classifier: Topic :: Internet :: WWW/HTTP :: Site Management
Provides-Extra: elasticsearch5
Provides-Extra: dandelion
Provides-Extra: gc_language
Provides-Extra: testing
Requires-Dist: wagtail (>=2.0)
Provides-Extra: dandelion
Requires-Dist: beautifulsoup4 (>=4.5.1); extra == 'dandelion'
Requires-Dist: html5lib (<1,>=0.999); extra == 'dandelion'
Requires-Dist: requests (<3.0,>=2.11.1); extra == 'dandelion'
Provides-Extra: elasticsearch5
Requires-Dist: elasticsearch (<6,>=5); extra == 'elasticsearch5'
Provides-Extra: gc_language
Requires-Dist: google-cloud-language (<0.30,>=0.29.0); extra == 'gc_language'
Requires-Dist: beautifulsoup4 (>=4.5.1); extra == 'gc_language'
Requires-Dist: html5lib (<1,>=0.999); extra == 'gc_language'
Provides-Extra: testing
Requires-Dist: flake8 (>=3.5.0); extra == 'testing'
Requires-Dist: isort (>=4.3.4); extra == 'testing'
